[
  {
    "code": "EKDV822",
    "title": "童貞は幼なじみに奪われました…初めて彼女のできた童貞のボクのためセックスの練習相手になってくれたいつもご機嫌な幼なじみ 花守夏歩",
    "size": "4.9 GB",
    "image_url": "https://pics.dmm.co.jp/mono/movie/adult/ekdv822/ekdv822pl.jpg",
    "torrent_url": "https://onejav.com/torrent/ekdv822/download/88071581/onejav.com_ekdv822.torrent",
    "tags": "Butt, Childhood Friend, Creampie, Cuckold, Footjob, Masturbation, Shaved, Skirt, Solowork, Uniform, Virgin Man",
    "actresses": "花守夏歩",
    "date": "2026-06-20",
    "page_url": "https://onejav.com/torrent/ekdv822"
  },
  {
    "code": "SQTE693",
    "title": "セフレ以上、恋人未満。コスプレ！中出し！性欲底なし美少女とハメ撮り三昧！ 花守夏歩",
    "size": "4.2 GB",
    "image_url": "https://pics.dmm.co.jp/mono/movie/adult/sqte693/sqte693pl.jpg",
    "torrent_url": "https://onejav.com/torrent/sqte693/download/28778850/onejav.com_sqte693.torrent",
    "tags": "Beautiful Girl, Blow, Cosplay, Creampie, POV, Solowork",
    "actresses": "花守夏歩",
    "date": "2026-06-13",
    "page_url": "https://onejav.com/torrent/sqte693"
  },
  {
    "code": "SUJI311",
    "title": "「こいつ舐めてるから詰むよ」昏●巨根無断挿入屈辱的快楽キメセク狂い堕ち生意気な塩対応女子に解らせマ●コ強●中出し謝罪パイパン●学生かほ 花守夏歩",
    "size": "5.3 GB",
    "image_url": "https://pics.dmm.co.jp/mono/movie/adult/suji311/suji311pl.jpg",
    "torrent_url": "https://onejav.com/torrent/suji311/download/11514024/onejav.com_suji311.torrent",
    "tags": "Beautiful Girl, Creampie, Drug, Evil, School Girls, Solowork",
    "actresses": "花守夏歩",
    "date": "2026-06-13",
    "page_url": "https://onejav.com/torrent/suji311"
  },
  {
    "code": "HMN877",
    "title": "保護女子集団里親譲渡会 身寄りのない娘たちに希望を。5人のマ○コをナマで確認して持ち帰れる激ヤバ施設に潜入！",
    "size": "5.3 GB",
    "image_url": "https://pics.dmm.co.jp/mono/movie/adult/hmn877/hmn877pl.jpg",
    "torrent_url": "https://onejav.com/torrent/hmn877/download/40710595/onejav.com_hmn877.torrent",
    "tags": "Creampie, Harem, Kiss, Mini, Orgy, Petite",
    "actresses": "谷村凪咲, 花守夏歩, 八森わか菜, 満島アンナ, 由良かな",
    "date": "2026-05-22",
    "page_url": "https://onejav.com/torrent/hmn877"
  },
  {
    "code": "SQTE683",
    "title": "いつでも使えるオナホ後輩 花守夏歩",
    "size": "4.6 GB",
    "image_url": "https://pics.dmm.co.jp/mono/movie/adult/sqte683/sqte683pl.jpg",
    "torrent_url": "https://onejav.com/torrent/sqte683/download/96421357/onejav.com_sqte683.torrent",
    "tags": "Beautiful Girl, Blow, Creampie, Masturbation, Solowork",
    "actresses": "花守夏歩",
    "date": "2026-05-16",
    "page_url": "https://onejav.com/torrent/sqte683"
  },
  {
    "code": "GVH843",
    "title": "僕のことが大好きな彼女のメンヘラ妹・夏歩ちゃんにひたすら束縛され続ける喜怒哀楽フェラチオ搾精生活。 花守夏歩",
    "size": "6.8 GB",
    "image_url": "https://pics.dmm.co.jp/mono/movie/adult/gvh843/gvh843pl.jpg",
    "torrent_url": "https://onejav.com/torrent/gvh843/download/67536685/onejav.com_gvh843.torrent",
    "tags": "Beautiful Girl, Blow, Cuckold, Huge Butt, Slut, Solowork",
    "actresses": "花守夏歩",
    "date": "2026-05-09",
    "page_url": "https://onejav.com/torrent/gvh843"
  },
  {
    "code": "MKMP727",
    "title": "小悪魔教え子2人に放課後ホテルに連れ込まれ…。どちらと付き合うか答えるまで、上下のクチでむさぼり奪い合い搾精させられた教育実習生のボク。",
    "size": "5.9 GB",
    "image_url": "https://pics.dmm.co.jp/mono/movie/adult/mkmp727/mkmp727pl.jpg",
    "torrent_url": "https://onejav.com/torrent/mkmp727/download/21490899/onejav.com_mkmp727.torrent",
    "tags": "Beautiful Girl, Harem, School Girls, Slut, Subjectivity",
    "actresses": "逢沢みゆ, 花守夏歩, 天羽りりか, 美咲音",
    "date": "2026-05-09",
    "page_url": "https://onejav.com/torrent/mkmp727"
  },
  {
    "code": "MKMP721",
    "title": "二人暮らしの父は寝たフリの私をオナホとして使っています。 花守夏歩",
    "size": "5.2 GB",
    "image_url": "https://pics.dmm.co.jp/mono/movie/adult/mkmp721/mkmp721pl.jpg",
    "torrent_url": "https://onejav.com/torrent/mkmp721/download/67730916/onejav.com_mkmp721.torrent",
    "tags": "Big Tits, Creampie, Drama, Incest, School Girls, Solowork",
    "actresses": "花守夏歩",
    "date": "2026-04-11",
    "page_url": "https://onejav.com/torrent/mkmp721"
  },
  {
    "code": "SQTE674",
    "title": "金玉からっぽにしてあげる。北岡果林×花守夏歩",
    "size": "4.3 GB",
    "image_url": "https://pics.dmm.co.jp/mono/movie/adult/sqte674/sqte674pl.jpg",
    "torrent_url": "https://onejav.com/torrent/sqte674/download/62032556/onejav.com_sqte674.torrent",
    "tags": "3P, 4P, Beautiful Girl, Blow, Creampie",
    "actresses": "北岡果林, 花守夏歩",
    "date": "2026-04-04",
    "page_url": "https://onejav.com/torrent/sqte674"
  },
  {
    "code": "MKMP713",
    "title": "誰にでも股を開く水泳部のヤリマン女子マネージャーたちに全身ぶっかけ42発！！スク水のままいつでもどこでもヤリまくり即ハメ乱交合宿",
    "size": "6.5 GB",
    "image_url": "https://pics.dmm.co.jp/mono/movie/adult/mkmp713/mkmp713pl.jpg",
    "torrent_url": "https://onejav.com/torrent/mkmp713/download/61914148/onejav.com_mkmp713.torrent",
    "tags": "Bukkake, Creampie, Facials, School Girls, School Swimsuit",
    "actresses": "逢沢みゆ, 花守夏歩, 天羽りりか",
    "date": "2026-03-21",
    "page_url": "https://onejav.com/torrent/mkmp713"
  }
]