[
  {
    "code": "FC2PPV4921135",
    "title": "FC2-PPV-4921135 【オトナのエロス】麗しの色白スレンダーな小学校のピアノ講師。恋する乙女を応援する生チンポ逆レッスン",
    "size": "7.4 GB",
    "image_url": "https://contents-thumbnail2.fc2.com/w1280/storage201000.contents.fc2.com/file/286/28519270/1781606394.14.jpg",
    "torrent_url": "https://onejav.com/torrent/fc2ppv4921135/download/18290033/onejav.com_fc2ppv4921135.torrent",
    "tags": "Amateur, Breasts, Butt, Creampie, FC2, Long Hair, POV, Sexy, Toy",
    "actresses": "",
    "date": "2026-06-17",
    "page_url": "https://onejav.com/torrent/fc2ppv4921135"
  },
  {
    "code": "FC2PPV4910243",
    "title": "FC2-PPV-4910243 【7日間限定セール】あどけなさの残る表情はたまらない♡エロスレンダーボディーでヌルズポ種搾りエステさせてきました。 【無修正・中出し】",
    "size": "5.3 GB",
    "image_url": "https://contents-thumbnail2.fc2.com/w1280/storage201000.contents.fc2.com/file/381/38031442/1780056652.67.png",
    "torrent_url": "https://onejav.com/torrent/fc2ppv4910243/download/31081302/onejav.com_fc2ppv4910243.torrent",
    "tags": "Amateur, Beautiful Girl, Blow, Breasts, Butt, Creampie, FC2, POV, Slender, Uncensored",
    "actresses": "",
    "date": "2026-06-17",
    "page_url": "https://onejav.com/torrent/fc2ppv4910243"
  },
  {
    "code": "FC2PPV4921181",
    "title": "FC2-PPV-4921181 【無】高身長の美尻って良いですね～、長い手足に超ミニセーラーコスの紐パン！似合い過ぎ⤴　ゴックン　中だし　※特典高画質",
    "size": "3.1 GB",
    "image_url": "https://contents-thumbnail2.fc2.com/w1280/storage200000.contents.fc2.com/file/381/38003297/1781482899.6.jpg",
    "torrent_url": "https://onejav.com/torrent/fc2ppv4921181/download/36511685/onejav.com_fc2ppv4921181.torrent",
    "tags": "Amateur, Beautiful Girl, Big Tits, Blow, Creampie, FC2, POV, Uncensored",
    "actresses": "",
    "date": "2026-06-17",
    "page_url": "https://onejav.com/torrent/fc2ppv4921181"
  },
  {
    "code": "FC2PPV4920811",
    "title": "FC2-PPV-4920811 【初撮り顔出し】田舎栃木から上京したての、清楚な音大生なこちゃん♡デブハゲキモオジの溜まりきった白濁汁を膣内に注ぎ込まれ受精不可避。",
    "size": "5.0 GB",
    "image_url": "https://contents-thumbnail2.fc2.com/w1280/storage200000.contents.fc2.com/file/377/37657565/1781381586.26.jpg",
    "torrent_url": "https://onejav.com/torrent/fc2ppv4920811/download/18805969/onejav.com_fc2ppv4920811.torrent",
    "tags": "Amateur, FC2",
    "actresses": "",
    "date": "2026-06-17",
    "page_url": "https://onejav.com/torrent/fc2ppv4920811"
  },
  {
    "code": "FC2PPV4921564",
    "title": "FC2-PPV-4921564 【初撮り】新人《3日間限定》陸上部元インターハイ準決勝出場選手 クラスのアイドルにスクールカースト底辺のデカチン突き上げ奥まで大量放出♥※未公開特典付き",
    "size": "9.1 GB",
    "image_url": "https://contents-thumbnail2.fc2.com/w1280/storage200000.contents.fc2.com/file/410/40976927/1781517418.06.png",
    "torrent_url": "https://onejav.com/torrent/fc2ppv4921564/download/87386456/onejav.com_fc2ppv4921564.torrent",
    "tags": "Amateur, Beautiful Girl, FC2, Slender, Uncensored",
    "actresses": "",
    "date": "2026-06-17",
    "page_url": "https://onejav.com/torrent/fc2ppv4921564"
  },
  {
    "code": "892OERO007",
    "title": "ナマ上等。…でもナカはやべぇだろwww ヤンキー上がりのギャル妻が性欲に負けてハメ撮り不倫。「まじ？うちからエッチなチューしてた？」って無自覚チン媚びしまくる奥さんを、壊れそうになるまでひたすらガン突きしてあげましたwww",
    "size": "2.6 GB",
    "image_url": "https://image.mgstage.com/images/kyantamaseisouin/892oero/007/pb_e_892oero-007.jpg",
    "torrent_url": "https://onejav.com/torrent/892oero007/download/64413397/onejav.com_892oero007.torrent",
    "tags": "Affair, Amateur, Big Tits, Creampie, Gal, Married Woman, POV",
    "actresses": "",
    "date": "2026-06-17",
    "page_url": "https://onejav.com/torrent/892oero007"
  },
  {
    "code": "FC2PPV4919888",
    "title": "FC2-PPV-4919888 真性ドMな元バレーボール選手あいりちゃん。172cm、Fカップのフィギュアボディをぞんざいにオナホ扱いし中出し。",
    "size": "4.6 GB",
    "image_url": "https://contents-thumbnail2.fc2.com/w1280/storage200000.contents.fc2.com/file/392/39120656/1781233100.8.png",
    "torrent_url": "https://onejav.com/torrent/fc2ppv4919888/download/15110104/onejav.com_fc2ppv4919888.torrent",
    "tags": "Amateur, Big Tits, Creampie, FC2, Slender",
    "actresses": "",
    "date": "2026-06-17",
    "page_url": "https://onejav.com/torrent/fc2ppv4919888"
  },
  {
    "code": "200GANA3393",
    "title": "乳首が薄ピンクの綺麗系お姉さんの、甘々ラブラブセックス！！所構わず指先をなぞるだけで魚のように跳ねる敏感女子！！イチャイチャ甘々からのトロトロセックス最高！！ 百戦錬磨のナンパ師のヤリ部屋で、連れ込みSEX隠し撮り 442",
    "size": "1.7 GB",
    "image_url": "https://image.mgstage.com/images/nanpatv/200gana/3393/pb_e_200gana-3393.jpg",
    "torrent_url": "https://onejav.com/torrent/200gana3393/download/33552956/onejav.com_200gana3393.torrent",
    "tags": "Amateur, Breasts, Huge Butt, Nampa, Voyeur",
    "actresses": "",
    "date": "2026-06-17",
    "page_url": "https://onejav.com/torrent/200gana3393"
  },
  {
    "code": "FC2PPV4921659",
    "title": "FC2-PPV-4921659 【シークレット版】【顔出し】【爆尻】都内ガールズバー勤務する「るな」さん、H100㎝超えの爆尻パンパン打ちつけ膣奥ガン突き絶頂SEX、こんなに突かれると頭おかしくなっちゃう！",
    "size": "4.1 GB",
    "image_url": "https://contents-thumbnail2.fc2.com/w1280/storage200000.contents.fc2.com/file/377/37664104/1781615639.04.jpg",
    "torrent_url": "https://onejav.com/torrent/fc2ppv4921659/download/77314973/onejav.com_fc2ppv4921659.torrent",
    "tags": "Amateur, Big Tits, Creampie, Electric Massager, FC2, Huge Butt, POV",
    "actresses": "",
    "date": "2026-06-17",
    "page_url": "https://onejav.com/torrent/fc2ppv4921659"
  },
  {
    "code": "FC2PPV4921972",
    "title": "FC2-PPV-4921972 【無修正】変態中出しおじさんナンパシリーズ第6弾：制服コスプレが似合いすぎるパイパン巨乳の可愛い子をナンパしてガチ生中出し",
    "size": "4.2 GB",
    "image_url": "https://contents-thumbnail2.fc2.com/w1280/storage201000.contents.fc2.com/file/411/41024541/1781587983.78.png",
    "torrent_url": "https://onejav.com/torrent/fc2ppv4921972/download/62053163/onejav.com_fc2ppv4921972.torrent",
    "tags": "Amateur, Beautiful Girl, Big Tits, FC2, Shaved, Uncensored",
    "actresses": "",
    "date": "2026-06-17",
    "page_url": "https://onejav.com/torrent/fc2ppv4921972"
  }
]