[
  {
    "code": "YUJ065",
    "title": "初めてセックスしたあの日から、最後の日まで。カラダの相性が良過ぎて、時間を忘れて毎日のようにヤリまくった一年間の同棲記録。",
    "size": "7.5 GB",
    "image_url": "https://pics.dmm.co.jp/mono/movie/adult/yuj065/yuj065pl.jpg",
    "torrent_url": "https://onejav.com/torrent/yuj065/download/57371924/onejav.com_yuj065.torrent",
    "tags": "Big Tits, Couple, Drama, Love, Slut, Solowork",
    "actresses": "Hikari Azusa",
    "date": "2026-07-03",
    "page_url": "https://onejav.com/torrent/yuj065"
  },
  {
    "code": "FNS232",
    "title": "スウェットの下に隠していたのは色白美巨乳 揉めば揉むほど淫乱になっていく絶倫彼女と初めてのお泊りイチャイチャセックス 神喜ミア",
    "size": "4.9 GB",
    "image_url": "https://cdn.faleno.net/top/wp-content/uploads/2026/06/FNS-232_1200.jpg?output-quality=60",
    "torrent_url": "https://onejav.com/torrent/fns232/download/88777371/onejav.com_fns232.torrent",
    "tags": "",
    "actresses": "神喜ミア",
    "date": "2026-07-05",
    "page_url": "https://onejav.com/torrent/fns232"
  },
  {
    "code": "YUJ068",
    "title": "",
    "size": "8.8 GB",
    "image_url": "https://pics.dmm.co.jp/mono/movie/adult/yuj068/yuj068pl.jpg",
    "torrent_url": "https://onejav.com/torrent/yuj068/download/28773983/onejav.com_yuj068.torrent",
    "tags": "",
    "actresses": "",
    "date": "2026-07-03",
    "page_url": "https://onejav.com/torrent/yuj068"
  },
  {
    "code": "WAAA662",
    "title": "",
    "size": "5.4 GB",
    "image_url": "https://pics.dmm.co.jp/mono/movie/adult/waaa662/waaa662pl.jpg",
    "torrent_url": "https://onejav.com/torrent/waaa662/download/79029488/onejav.com_waaa662.torrent",
    "tags": "",
    "actresses": "",
    "date": "2026-07-03",
    "page_url": "https://onejav.com/torrent/waaa662"
  },
  {
    "code": "300MIUM1395",
    "title": "スケベ顔で迫る変態ジト目ま◯こww本人はSに見られるって言ってるけど、目がもうドMの瞳してるんよね。「挿れて…くれるよね？」期待でいっぱいのイヤらしい目つきで御法度チ◯ポおねだりww待望の挿入でグネグネと止まらない腰。。ドMの女って騎乗位慣れてるよなww ：file.43",
    "size": "3.6 GB",
    "image_url": "https://image.mgstage.com/images/prestigepremium/300mium/1395/pb_e_300mium-1395.jpg",
    "torrent_url": "https://onejav.com/torrent/300mium1395/download/22362004/onejav.com_300mium1395.torrent",
    "tags": "Amateur, Big Tits, Butt, Electric Massager, Lotion, Voyeur",
    "actresses": "",
    "date": "2026-07-05",
    "page_url": "https://onejav.com/torrent/300mium1395"
  },
  {
    "code": "892OERO008",
    "title": "旦那に内緒でトキメキたい欲求不満な人妻ナースとハメ撮り不倫。ギン勃ちチ◯ポを「可愛がってもいいの？」とあまあまご奉仕してくれるデカ尻巨乳な人妻ちゃん。清楚で上品な奥さんが、快楽でどんどんバカになってオホイキ絶頂。潮吹き連発。そんなどすけべマ◯コにどっぷり中出し。",
    "size": "2.8 GB",
    "image_url": "https://image.mgstage.com/images/kyantamaseisouin/892oero/008/pb_e_892oero-008.jpg",
    "torrent_url": "https://onejav.com/torrent/892oero008/download/62499194/onejav.com_892oero008.torrent",
    "tags": "Affair, Amateur, Big Tits, Creampie, Married Woman, POV, Squirting",
    "actresses": "",
    "date": "2026-07-02",
    "page_url": "https://onejav.com/torrent/892oero008"
  },
  {
    "code": "MIKR107",
    "title": "",
    "size": "7.1 GB",
    "image_url": "https://pics.dmm.co.jp/mono/movie/adult/mikr107/mikr107pl.jpg",
    "torrent_url": "https://onejav.com/torrent/mikr107/download/71801651/onejav.com_mikr107.torrent",
    "tags": "",
    "actresses": "",
    "date": "2026-07-03",
    "page_url": "https://onejav.com/torrent/mikr107"
  },
  {
    "code": "ABF364",
    "title": "平日女教師、週末オナホ。 鈴村あいり",
    "size": "4.7 GB",
    "image_url": "https://image.mgstage.com/images/prestige/abf/364/pb_e_abf-364.jpg",
    "torrent_url": "https://onejav.com/torrent/abf364/download/87408202/onejav.com_abf364.torrent",
    "tags": "Breasts, Butt, Cosplay, Creampie, Female Teacher, Solowork",
    "actresses": "Airi Suzumura",
    "date": "2026-07-02",
    "page_url": "https://onejav.com/torrent/abf364"
  },
  {
    "code": "FC2PPV4933359",
    "title": "FC2-PPV-4933359 絶頂回数30回超え⁉️男性経験少ないメンエス嬢がハメ撮り体験で本能覚醒！モニター越しに自分の痴態を見ながらガチイキする黒髪美**のヤバいやつ",
    "size": "5.4 GB",
    "image_url": "https://contents-thumbnail2.fc2.com/w1280/storage201000.contents.fc2.com/file/388/38703450/1783130999.06.jpg",
    "torrent_url": "https://onejav.com/torrent/fc2ppv4933359/download/83711324/onejav.com_fc2ppv4933359.torrent",
    "tags": "Amateur, Black Hair, Creampie, FC2, POV, Uncensored",
    "actresses": "",
    "date": "2026-07-05",
    "page_url": "https://onejav.com/torrent/fc2ppv4933359"
  },
  {
    "code": "XVSR884",
    "title": "大嫌いな義父の邪悪な舌使いに犯●れた人妻の二日間 響蓮",
    "size": "7.5 GB",
    "image_url": "https://pics.dmm.co.jp/mono/movie/adult/xvsr884/xvsr884pl.jpg",
    "torrent_url": "https://onejav.com/torrent/xvsr884/download/15557891/onejav.com_xvsr884.torrent",
    "tags": "Creampie, Cuckold, Married Woman, Slender, Solowork, Squirting",
    "actresses": "響蓮",
    "date": "2026-07-04",
    "page_url": "https://onejav.com/torrent/xvsr884"
  }
]